{
	"name": "ds_ott_adf_to_onprem_for_copy_activity",
	"properties": {
		"linkedServiceName": {
			"referenceName": "ls_ott_adf_to_onprem_for_copy_activity",
			"type": "LinkedServiceReference"
		},
		"parameters": {
			"FileName": {
				"type": "string"
			}
		},
		"folder": {
			"name": "DS_OTTProject"
		},
		"annotations": [],
		"type": "DelimitedText",
		"typeProperties": {
			"location": {
				"type": "FileServerLocation",
				"fileName": {
					"value": "@dataset().FileName",
					"type": "Expression"
				}
			},
			"columnDelimiter": ",",
			"escapeChar": "\\",
			"firstRowAsHeader": true,
			"quoteChar": "\""
		},
		"schema": []
	},
	"type": "Microsoft.DataFactory/factories/datasets"
}